{
    "Items": [
        {
            "YearMonth": "2024/03",
            "USDRatePerDollar": "149.543891",
            "MMKRatePerYen": "23.000000",
            "DayTime": "09 00:21"
        },
        {
            "YearMonth": "2024/03",
            "USDRatePerDollar": "149.543891",
            "MMKRatePerYen": "23.000000",
            "DayTime": "09 01:20"
        },
        {
            "YearMonth": "2024/03",
            "USDRatePerDollar": "149.543891",
            "MMKRatePerYen": "23.000000",
            "DayTime": "09 02:20"
        },
        {
            "YearMonth": "2024/03",
            "USDRatePerDollar": "149.543891",
            "MMKRatePerYen": "23.000000",
            "DayTime": "09 03:20"
        },
        {
            "YearMonth": "2024/03",
            "USDRatePerDollar": "149.543891",
            "MMKRatePerYen": "23.000000",
            "DayTime": "09 04:20"
        },
        {
            "YearMonth": "2024/03",
            "USDRatePerDollar": "149.543891",
            "MMKRatePerYen": "23.000000",
            "DayTime": "09 05:20"
        },
        {
            "YearMonth": "2024/03",
            "USDRatePerDollar": "149.543891",
            "MMKRatePerYen": "23.000000",
            "DayTime": "09 06:20"
        },
        {
            "YearMonth": "2024/03",
            "USDRatePerDollar": "149.543891",
            "MMKRatePerYen": "23.000000",
            "DayTime": "09 07:20"
        }
    ],
    "Count": 8,
    "ScannedCount": 8
}