{
    "Items": [
        {
            "YearMonth": "2022/04",
            "USDRatePerDollar": "126.871352",
            "CashPickupDateTime": "2022/04/12 23:00",
            "DayTime": "13 00:20",
            "CashPickupMMKRatePerYen": "14.730000",
            "MMKRatePerYen": "14.721068"
        },
        {
            "YearMonth": "2022/04",
            "USDRatePerDollar": "126.871352",
            "CashPickupDateTime": "2022/04/13 00:00",
            "DayTime": "13 01:20",
            "CashPickupMMKRatePerYen": "14.730000",
            "MMKRatePerYen": "14.721068"
        },
        {
            "YearMonth": "2022/04",
            "USDRatePerDollar": "126.871352",
            "CashPickupDateTime": "2022/04/13 01:00",
            "DayTime": "13 02:20",
            "CashPickupMMKRatePerYen": "14.730000",
            "MMKRatePerYen": "14.721068"
        }
    ],
    "Count": 3,
    "ScannedCount": 3
}