{
    "Items": [
        {
            "YearMonth": "2022/10",
            "USDRatePerDollar": "150.262960",
            "CashPickupDateTime": "2022/10/17 23:00",
            "DayTime": "18 00:20",
            "CashPickupMMKRatePerYen": "19.062584",
            "MMKRatePerYen": "19.066420"
        },
        {
            "YearMonth": "2022/10",
            "USDRatePerDollar": "150.262960",
            "CashPickupDateTime": "2022/10/18 00:00",
            "DayTime": "18 01:20",
            "CashPickupMMKRatePerYen": "19.062584",
            "MMKRatePerYen": "19.066420"
        },
        {
            "YearMonth": "2022/10",
            "USDRatePerDollar": "150.262960",
            "CashPickupDateTime": "2022/10/18 01:00",
            "DayTime": "18 02:20",
            "CashPickupMMKRatePerYen": "19.062584",
            "MMKRatePerYen": "19.066420"
        },
        {
            "YearMonth": "2022/10",
            "USDRatePerDollar": "150.262960",
            "CashPickupDateTime": "2022/10/18 03:00",
            "DayTime": "18 03:20",
            "CashPickupMMKRatePerYen": "19.062584",
            "MMKRatePerYen": "19.066420"
        },
        {
            "YearMonth": "2022/10",
            "USDRatePerDollar": "150.262960",
            "CashPickupDateTime": "2022/10/18 03:00",
            "DayTime": "18 04:20",
            "CashPickupMMKRatePerYen": "19.062584",
            "MMKRatePerYen": "19.066420"
        },
        {
            "YearMonth": "2022/10",
            "USDRatePerDollar": "150.262960",
            "CashPickupDateTime": "2022/10/18 04:00",
            "DayTime": "18 05:20",
            "CashPickupMMKRatePerYen": "19.062584",
            "MMKRatePerYen": "19.066420"
        },
        {
            "YearMonth": "2022/10",
            "USDRatePerDollar": "150.262960",
            "CashPickupDateTime": "2022/10/18 05:00",
            "DayTime": "18 06:20",
            "CashPickupMMKRatePerYen": "19.062584",
            "MMKRatePerYen": "19.066420"
        },
        {
            "YearMonth": "2022/10",
            "USDRatePerDollar": "150.693188",
            "CashPickupDateTime": "2022/10/18 06:00",
            "DayTime": "18 07:20",
            "CashPickupMMKRatePerYen": "19.062584",
            "MMKRatePerYen": "19.066420"
        },
        {
            "YearMonth": "2022/10",
            "USDRatePerDollar": "150.693188",
            "CashPickupDateTime": "2022/10/18 07:00",
            "DayTime": "18 08:20",
            "CashPickupMMKRatePerYen": "19.062584",
            "MMKRatePerYen": "19.066420"
        },
        {
            "YearMonth": "2022/10",
            "USDRatePerDollar": "150.693188",
            "CashPickupDateTime": "2022/10/18 08:00",
            "DayTime": "18 09:20",
            "CashPickupMMKRatePerYen": "19.062584",
            "MMKRatePerYen": "19.066420"
        },
        {
            "YearMonth": "2022/10",
            "USDRatePerDollar": "150.693188",
            "CashPickupDateTime": "2022/10/18 09:00",
            "DayTime": "18 10:20",
            "CashPickupMMKRatePerYen": "19.062584",
            "MMKRatePerYen": "19.066420"
        },
        {
            "YearMonth": "2022/10",
            "USDRatePerDollar": "150.69",
            "CashPickupDateTime": "2022/10/18 10:00",
            "DayTime": "18 10:40",
            "CashPickupMMKRatePerYen": "19.050000",
            "MMKRatePerYen": "19.053959"
        }
    ],
    "Count": 12,
    "ScannedCount": 12
}