{
    "Items": [
        {
            "YearMonth": "2023/06",
            "USDRatePerDollar": "140.825235",
            "CashPickupDateTime": "2023/06/07 23:00",
            "DayTime": "08 00:20",
            "CashPickupMMKRatePerYen": "20.530000",
            "MMKRatePerYen": "20.520050"
        },
        {
            "YearMonth": "2023/06",
            "USDRatePerDollar": "140.825235",
            "CashPickupDateTime": "2023/06/08 01:00",
            "DayTime": "08 01:20",
            "CashPickupMMKRatePerYen": "20.530000",
            "MMKRatePerYen": "20.520050"
        },
        {
            "YearMonth": "2023/06",
            "USDRatePerDollar": "140.825235",
            "CashPickupDateTime": "2023/06/08 02:00",
            "DayTime": "08 02:20",
            "CashPickupMMKRatePerYen": "20.530000",
            "MMKRatePerYen": "20.520050"
        },
        {
            "YearMonth": "2023/06",
            "USDRatePerDollar": "140.825235",
            "CashPickupDateTime": "2023/06/08 03:00",
            "DayTime": "08 03:20",
            "CashPickupMMKRatePerYen": "20.530000",
            "MMKRatePerYen": "20.520050"
        },
        {
            "YearMonth": "2023/06",
            "USDRatePerDollar": "140.825235",
            "CashPickupDateTime": "2023/06/08 03:00",
            "DayTime": "08 04:20",
            "CashPickupMMKRatePerYen": "20.530000",
            "MMKRatePerYen": "20.520050"
        },
        {
            "YearMonth": "2023/06",
            "USDRatePerDollar": "140.825235",
            "CashPickupDateTime": "2023/06/08 04:00",
            "DayTime": "08 05:20",
            "CashPickupMMKRatePerYen": "20.530000",
            "MMKRatePerYen": "20.520050"
        },
        {
            "YearMonth": "2023/06",
            "USDRatePerDollar": "140.825235",
            "CashPickupDateTime": "2023/06/08 05:00",
            "DayTime": "08 06:20",
            "CashPickupMMKRatePerYen": "20.530000",
            "MMKRatePerYen": "20.520050"
        },
        {
            "YearMonth": "2023/06",
            "USDRatePerDollar": "140.825235",
            "CashPickupDateTime": "2023/06/08 06:00",
            "DayTime": "08 07:20",
            "CashPickupMMKRatePerYen": "20.530000",
            "MMKRatePerYen": "20.520050"
        },
        {
            "YearMonth": "2023/06",
            "USDRatePerDollar": "141.723356",
            "CashPickupDateTime": "2023/06/08 07:00",
            "DayTime": "08 08:20",
            "CashPickupMMKRatePerYen": "20.530000",
            "MMKRatePerYen": "20.520050"
        },
        {
            "YearMonth": "2023/06",
            "USDRatePerDollar": "141.72",
            "MMKRatePerYen": "20.520050",
            "DayTime": "08 09:10"
        },
        {
            "YearMonth": "2023/06",
            "USDRatePerDollar": "141.723356",
            "CashPickupDateTime": "2023/06/08 08:00",
            "DayTime": "08 09:20",
            "CashPickupMMKRatePerYen": "20.530000",
            "MMKRatePerYen": "20.520050"
        },
        {
            "YearMonth": "2023/06",
            "USDRatePerDollar": "141.72",
            "CashPickupDateTime": "2023/06/08 09:00",
            "DayTime": "08 09:55",
            "CashPickupMMKRatePerYen": "20.530000",
            "MMKRatePerYen": "20.520050"
        },
        {
            "YearMonth": "2023/06",
            "USDRatePerDollar": "141.72",
            "MMKRatePerYen": "20.520050",
            "DayTime": "08 10:10"
        },
        {
            "YearMonth": "2023/06",
            "USDRatePerDollar": "141.723356",
            "CashPickupDateTime": "2023/06/08 09:00",
            "DayTime": "08 10:20",
            "CashPickupMMKRatePerYen": "20.530000",
            "MMKRatePerYen": "20.520050"
        },
        {
            "errorMessage": "2023-06-08T01:28:55.120Z 5bfeea3d-21a6-4286-bd58-21f5efc80ec7 Task timed out after 45.05 seconds",
            "YearMonth": "2023/06",
            "USDRatePerDollar": "141.72",
            "MMKRatePerYen": "20.452320",
            "DayTime": "08 10:25"
        },
        {
            "YearMonth": "2023/06",
            "USDRatePerDollar": "141.72",
            "CashPickupDateTime": "2023/06/08 10:00",
            "DayTime": "08 10:40",
            "CashPickupMMKRatePerYen": "20.460000",
            "MMKRatePerYen": "20.452320"
        },
        {
            "YearMonth": "2023/06",
            "USDRatePerDollar": "141.723356",
            "MMKRatePerYen": "20.452320",
            "DayTime": "08 11:20"
        },
        {
            "YearMonth": "2023/06",
            "USDRatePerDollar": "141.72",
            "MMKRatePerYen": "20.452320",
            "DayTime": "08 11:25"
        },
        {
            "YearMonth": "2023/06",
            "USDRatePerDollar": "141.723356",
            "CashPickupDateTime": "2023/06/08 11:00",
            "DayTime": "08 12:20",
            "CashPickupMMKRatePerYen": "20.460000",
            "MMKRatePerYen": "20.452320"
        },
        {
            "YearMonth": "2023/06",
            "USDRatePerDollar": "141.382723",
            "CashPickupDateTime": "2023/06/08 12:00",
            "DayTime": "08 13:20",
            "CashPickupMMKRatePerYen": "20.460000",
            "MMKRatePerYen": "20.452320"
        },
        {
            "YearMonth": "2023/06",
            "USDRatePerDollar": "141.38",
            "CashPickupDateTime": "2023/06/08 12:00",
            "DayTime": "08 13:25",
            "CashPickupMMKRatePerYen": "20.460000",
            "MMKRatePerYen": "20.452320"
        },
        {
            "YearMonth": "2023/06",
            "USDRatePerDollar": "141.38",
            "MMKRatePerYen": "20.452320",
            "DayTime": "08 14:05"
        }
    ],
    "Count": 22,
    "ScannedCount": 22
}