{
    "Items": [
        {
            "YearMonth": "2022/03",
            "USDRatePerDollar": "123.456790",
            "CashPickupDateTime": "2022/03/27 23:00",
            "DayTime": "28 00:20",
            "CashPickupMMKRatePerYen": "14.544000",
            "MMKRatePerYen": "14.552000"
        },
        {
            "YearMonth": "2022/03",
            "USDRatePerDollar": "123.456790",
            "CashPickupDateTime": "2022/03/28 00:00",
            "DayTime": "28 01:20",
            "CashPickupMMKRatePerYen": "14.544000",
            "MMKRatePerYen": "14.552000"
        },
        {
            "YearMonth": "2022/03",
            "USDRatePerDollar": "123.456790",
            "CashPickupDateTime": "2022/03/28 01:00",
            "DayTime": "28 02:20",
            "CashPickupMMKRatePerYen": "14.544000",
            "MMKRatePerYen": "14.552000"
        },
        {
            "YearMonth": "2022/03",
            "USDRatePerDollar": "123.456790",
            "CashPickupDateTime": "2022/03/28 03:00",
            "DayTime": "28 03:20",
            "CashPickupMMKRatePerYen": "14.544000",
            "MMKRatePerYen": "14.552000"
        },
        {
            "YearMonth": "2022/03",
            "USDRatePerDollar": "123.456790",
            "MMKRatePerYen": "14.552000",
            "DayTime": "28 04:20"
        },
        {
            "YearMonth": "2022/03",
            "USDRatePerDollar": "123.456790",
            "CashPickupDateTime": "2022/03/28 04:00",
            "DayTime": "28 05:20",
            "CashPickupMMKRatePerYen": "14.544000",
            "MMKRatePerYen": "14.552000"
        },
        {
            "YearMonth": "2022/03",
            "USDRatePerDollar": "123.456790",
            "MMKRatePerYen": "14.552000",
            "DayTime": "28 06:20"
        },
        {
            "YearMonth": "2022/03",
            "USDRatePerDollar": "123.456790",
            "MMKRatePerYen": "14.552000",
            "DayTime": "28 07:20"
        },
        {
            "YearMonth": "2022/03",
            "USDRatePerDollar": "123.456790",
            "CashPickupDateTime": "2022/03/28 07:00",
            "DayTime": "28 08:20",
            "CashPickupMMKRatePerYen": "14.544000",
            "MMKRatePerYen": "14.552000"
        },
        {
            "YearMonth": "2022/03",
            "USDRatePerDollar": "123.456790",
            "CashPickupDateTime": "2022/03/28 08:00",
            "DayTime": "28 09:20",
            "CashPickupMMKRatePerYen": "14.544000",
            "MMKRatePerYen": "14.552000"
        },
        {
            "YearMonth": "2022/03",
            "USDRatePerDollar": "123.45",
            "CashPickupDateTime": "2022/03/28 09:00",
            "DayTime": "28 10:05",
            "CashPickupMMKRatePerYen": "14.544000",
            "MMKRatePerYen": "14.552000"
        },
        {
            "YearMonth": "2022/03",
            "USDRatePerDollar": "123.456790",
            "CashPickupDateTime": "2022/03/28 09:00",
            "DayTime": "28 10:20",
            "CashPickupMMKRatePerYen": "14.535000",
            "MMKRatePerYen": "14.552000"
        },
        {
            "YearMonth": "2022/03",
            "USDRatePerDollar": "123.45",
            "CashPickupDateTime": "2022/03/28 10:00",
            "DayTime": "28 10:40",
            "CashPickupMMKRatePerYen": "14.535000",
            "MMKRatePerYen": "14.530591"
        },
        {
            "YearMonth": "2022/03",
            "USDRatePerDollar": "123.45",
            "CashPickupDateTime": "2022/03/28 10:00",
            "DayTime": "28 10:45",
            "CashPickupMMKRatePerYen": "14.535000",
            "MMKRatePerYen": "14.530591"
        },
        {
            "YearMonth": "2022/03",
            "USDRatePerDollar": "123.45",
            "CashPickupDateTime": "2022/03/28 10:00",
            "DayTime": "28 10:55",
            "CashPickupMMKRatePerYen": "14.535000",
            "MMKRatePerYen": "14.530591"
        },
        {
            "YearMonth": "2022/03",
            "USDRatePerDollar": "123.45",
            "CashPickupDateTime": "2022/03/28 10:00",
            "DayTime": "28 11:05",
            "CashPickupMMKRatePerYen": "14.535000",
            "MMKRatePerYen": "14.530591"
        },
        {
            "YearMonth": "2022/03",
            "USDRatePerDollar": "123.456790",
            "CashPickupDateTime": "2022/03/28 10:00",
            "DayTime": "28 11:20",
            "CashPickupMMKRatePerYen": "14.535000",
            "MMKRatePerYen": "14.530591"
        },
        {
            "YearMonth": "2022/03",
            "USDRatePerDollar": "123.45",
            "CashPickupDateTime": "2022/03/28 10:00",
            "DayTime": "28 11:25",
            "CashPickupMMKRatePerYen": "14.535000",
            "MMKRatePerYen": "14.530591"
        },
        {
            "YearMonth": "2022/03",
            "USDRatePerDollar": "123.456790",
            "CashPickupDateTime": "2022/03/28 11:00",
            "DayTime": "28 12:20",
            "CashPickupMMKRatePerYen": "14.535000",
            "MMKRatePerYen": "14.530591"
        },
        {
            "YearMonth": "2022/03",
            "USDRatePerDollar": "123.45",
            "CashPickupDateTime": "2022/03/28 12:00",
            "DayTime": "28 12:30",
            "CashPickupMMKRatePerYen": "14.535000",
            "MMKRatePerYen": "14.530591"
        },
        {
            "YearMonth": "2022/03",
            "USDRatePerDollar": "124.331717",
            "MMKRatePerYen": "14.530591",
            "DayTime": "28 13:20"
        },
        {
            "YearMonth": "2022/03",
            "USDRatePerDollar": "124.33",
            "CashPickupDateTime": "2022/03/28 13:00",
            "DayTime": "28 13:40",
            "CashPickupMMKRatePerYen": "14.535000",
            "MMKRatePerYen": "14.530591"
        },
        {
            "YearMonth": "2022/03",
            "USDRatePerDollar": "124.33",
            "CashPickupDateTime": "2022/03/28 13:00",
            "DayTime": "28 14:10",
            "CashPickupMMKRatePerYen": "14.535000",
            "MMKRatePerYen": "14.530591"
        },
        {
            "YearMonth": "2022/03",
            "USDRatePerDollar": "124.331717",
            "CashPickupDateTime": "2022/03/28 13:00",
            "DayTime": "28 14:20",
            "CashPickupMMKRatePerYen": "14.535000",
            "MMKRatePerYen": "14.530591"
        },
        {
            "YearMonth": "2022/03",
            "USDRatePerDollar": "124.33",
            "CashPickupDateTime": "2022/03/28 13:00",
            "DayTime": "28 14:25",
            "CashPickupMMKRatePerYen": "14.535000",
            "MMKRatePerYen": "14.530591"
        }
    ],
    "Count": 25,
    "ScannedCount": 25
}