{
    "Items": [
        {
            "YearMonth": "2023/12",
            "USDRatePerDollar": "142.653352",
            "MMKRatePerYen": "23.830000",
            "DayTime": "31 00:21"
        },
        {
            "YearMonth": "2023/12",
            "USDRatePerDollar": "142.653352",
            "MMKRatePerYen": "23.830000",
            "DayTime": "31 01:20"
        },
        {
            "YearMonth": "2023/12",
            "USDRatePerDollar": "142.653352",
            "MMKRatePerYen": "23.830000",
            "DayTime": "31 02:20"
        },
        {
            "YearMonth": "2023/12",
            "USDRatePerDollar": "142.653352",
            "MMKRatePerYen": "23.830000",
            "DayTime": "31 03:20"
        },
        {
            "YearMonth": "2023/12",
            "USDRatePerDollar": "142.653352",
            "MMKRatePerYen": "23.830000",
            "DayTime": "31 04:20"
        },
        {
            "YearMonth": "2023/12",
            "USDRatePerDollar": "142.653352",
            "MMKRatePerYen": "23.830000",
            "DayTime": "31 05:20"
        },
        {
            "YearMonth": "2023/12",
            "USDRatePerDollar": "142.653352",
            "MMKRatePerYen": "23.830000",
            "DayTime": "31 06:20"
        },
        {
            "YearMonth": "2023/12",
            "USDRatePerDollar": "142.653352",
            "MMKRatePerYen": "23.830000",
            "DayTime": "31 07:20"
        },
        {
            "YearMonth": "2023/12",
            "USDRatePerDollar": "142.653352",
            "MMKRatePerYen": "23.830000",
            "DayTime": "31 08:20"
        },
        {
            "YearMonth": "2023/12",
            "USDRatePerDollar": "142.65",
            "MMKRatePerYen": "23.830000",
            "DayTime": "31 09:10"
        },
        {
            "YearMonth": "2023/12",
            "USDRatePerDollar": "142.653352",
            "MMKRatePerYen": "23.830000",
            "DayTime": "31 09:20"
        },
        {
            "YearMonth": "2023/12",
            "USDRatePerDollar": "142.65",
            "MMKRatePerYen": "23.830000",
            "DayTime": "31 10:20"
        },
        {
            "YearMonth": "2023/12",
            "USDRatePerDollar": "142.65",
            "MMKRatePerYen": "23.830000",
            "DayTime": "31 10:40"
        },
        {
            "YearMonth": "2023/12",
            "USDRatePerDollar": "142.65",
            "MMKRatePerYen": "23.830000",
            "DayTime": "31 11:20"
        },
        {
            "YearMonth": "2023/12",
            "USDRatePerDollar": "142.653352",
            "MMKRatePerYen": "23.830000",
            "DayTime": "31 12:20"
        },
        {
            "YearMonth": "2023/12",
            "USDRatePerDollar": "142.653352",
            "MMKRatePerYen": "23.830000",
            "DayTime": "31 13:20"
        },
        {
            "YearMonth": "2023/12",
            "USDRatePerDollar": "142.65",
            "MMKRatePerYen": "23.830000",
            "DayTime": "31 14:10"
        },
        {
            "YearMonth": "2023/12",
            "USDRatePerDollar": "142.653352",
            "MMKRatePerYen": "23.830000",
            "DayTime": "31 14:20"
        },
        {
            "YearMonth": "2023/12",
            "USDRatePerDollar": "142.653352",
            "MMKRatePerYen": "23.830000",
            "DayTime": "31 15:20"
        },
        {
            "YearMonth": "2023/12",
            "USDRatePerDollar": "142.653352",
            "MMKRatePerYen": "23.830000",
            "DayTime": "31 16:20"
        },
        {
            "YearMonth": "2023/12",
            "USDRatePerDollar": "142.653352",
            "MMKRatePerYen": "23.830000",
            "DayTime": "31 17:20"
        },
        {
            "YearMonth": "2023/12",
            "USDRatePerDollar": "142.653352",
            "MMKRatePerYen": "23.830000",
            "DayTime": "31 18:20"
        },
        {
            "YearMonth": "2023/12",
            "USDRatePerDollar": "142.653352",
            "MMKRatePerYen": "23.830000",
            "DayTime": "31 19:20"
        },
        {
            "YearMonth": "2023/12",
            "USDRatePerDollar": "142.653352",
            "MMKRatePerYen": "23.830000",
            "DayTime": "31 20:20"
        },
        {
            "YearMonth": "2023/12",
            "USDRatePerDollar": "142.653352",
            "MMKRatePerYen": "23.830000",
            "DayTime": "31 21:20"
        }
    ],
    "Count": 25,
    "ScannedCount": 25
}